edtrace/__init__.py
edtrace/arxiv_util.py
edtrace/examples.py
edtrace/execute.py
edtrace/execute_util.py
edtrace/file_util.py
edtrace/reference.py
edtrace-0.1.11.dist-info/METADATA
edtrace-0.1.11.dist-info/WHEEL
edtrace-0.1.11.dist-info/top_level.txt
edtrace-0.1.11.dist-info/RECORD
