Metadata-Version: 2.4
Name: edtrace
Version: 0.1.11
Summary: Library for tracing through Python programs for educational presentation
Requires-Python: >=3.11
Requires-Dist: torch
Requires-Dist: sympy
Requires-Dist: numpy
Requires-Dist: requests
